{
	"chapterEn": "Chapter 21",
	"chapterAs": "ܩܦܠܐܘܢ: ܟܐ.",
	"verses": [
		{
			"verseNumberEn": "1",
			"verseNumberAs": "ܐ",
			"verseText": "ܘܡܵܪܝܵܐ ܣܘܼܚܒܸܪܹܐ ܠܣܲܪܵܐ: ܕܵܐܟ̣ܝܼ ܕܐ݇ܡܸܪܹܐ: ܘܥܒܸܕܠܹܐ ܡܵܪܝܵܐ ܠܣܲܪܵܐ ܕܵܐܟ̣ܝܼ ܕܗܘܼܡܙܸܡܠܹܐ."
		},
		{
			"verseNumberEn": "2",
			"verseNumberAs": "ܒ",
			"verseText": "ܘܒܛܸܢܵܐ: ܘܝ݇ܠܸܕܠܵܐ ܣܲܪܵܐ ܠܐܲܒ̣ܪܵܗܵܡ ܒܪܘܼܢܵܐ ܒܣܲܝܒ̇ܘܼܬܘܼܗܝ: ܒܙܲܒ̣ܢܵܐ ܕܘܲܥܕܵܐ ܕܗܘܼܡܙܸܡܠܹܐ ܥܲܡܹܗ ܐܲܠܵܗܵܐ."
		},
		{
			"verseNumberEn": "3",
			"verseNumberAs": "ܓ",
			"verseText": "ܘܩܪܹܠܹܐ ܐܲܒ̣ܪܵܗܵܡ ܫܸܡܵܐ ܕܒܪܘܼܢܘܼܗܝ: ܕܦܸܫܠܹܐ ܗ݇ܘܝܼܵܐ ܐܸܠܹܗ: ܕܝ݇ܠܸܕܠܵܐ ܩܵܬܹܗ ܣܲܪܵܐ: ܐܝܼܣܚܵܩ."
		},
		{
			"verseNumberEn": "4",
			"verseNumberAs": "ܕ",
			"verseText": "ܘܓܙܸܪܹܐ ܐܲܒ̣ܪܵܗܵܡ ܠܐܝܼܣܚܵܩ ܒܪܘܼܢܘܼܗܝ ܒܲܪ ܬܡܵܢܝܵܐ ܝܘܿܡܵܢܹ̈ܐ: ܕܵܐܟ̣ܝܼ ܕܦܘܼܩܸܕܠܹܐ ܐܸܠܹܗ ܐܲܠܵܗܵܐ."
		},
		{
			"verseNumberEn": "5",
			"verseNumberAs": "ܗ",
			"verseText": "ܘܐܲܒ̣ܪܵܗܵܡ ܒܲܪ ܡܵܐܐ ܫܸܢܹ̈ܐ ܗ݇ܘܵܐ ܟܲܕ ܦܸܫܠܹܐ ܝ݇ܠܝܼܕܵܐ ܐܸܠܹܗ ܐܝܼܣܚܵܩ ܒܪܘܼܢܘܼܗܝ."
		},
		{
			"verseNumberEn": "6",
			"verseNumberAs": "ܘ",
			"verseText": "ܘܐ݇ܡܸܪܵܐ ܣܲܪܵܐ: ܓܸܚܟܵܐ ܥܒܸܕܠܹܐ ܐܸܠܝܼ ܐܲܠܵܗܵܐ: ܟܠ ܕܫܲܡܸܥ ܒܸܬ ܓܵܚܸܟ ܒܘܼܬ ܕܝܼܝܼ."
		},
		{
			"verseNumberEn": "7",
			"verseNumberAs": "ܙ",
			"verseText": "ܘܐ݇ܡܸܪܵܐ: ܡܵܢܝܼ ܐܵܡܸܪ ܗ݇ܘܵܐ ܠܐܲܒ̣ܪܵܗܵܡ: ܕܡܲܡܸܨܵܐ ܒܢܘܼܢܹ̈ܐ ܣܲܪܵܐ: ܣܵܒܵܒ̇ ܕܝ݇ܠܸܕܠܝܼ ܒܪܘܼܢܵܐ ܒܣܲܝܒ̇ܘܼܬܘܼܗܝ."
		},
		{
			"verseNumberEn": "8",
			"verseNumberAs": "ܚ",
			"verseText": "ܘܓܘܼܪܘܸܣܠܹܐ ܝܵܠܵܐ: ܘܦܸܫܠܹܐ ܚܣܝܼܠܵܐ: ܘܥܒܸܕܠܹܐ ܐܲܒ̣ܪܵܗܵܡ ܐܲܪܚܘܼܬܵܐ ܓܘܼܪܬܵܐ ܒܝܘܿܡܵܐ ܕܦܸܫܠܹܐ ܚܣܝܼܠܵܐ ܐܝܼܣܚܵܩ."
		},
		{
			"verseNumberEn": "9",
			"verseNumberAs": "ܛ",
			"verseText": "ܘܚܙܹܠܵܐ ܣܲܪܵܐ ܠܒܪܘܼܢܵܐ ܕܗܵ‍ܓ̣ܵܪ ܡܸܨܪܵܝܬܵܐ: ܕܝ݇ܠܸܕܠܵܐ ܠܐܲܒ̣ܪܵܗܵܡ: ܒܸܓܚܵܟܵܐ."
		},
		{
			"verseNumberEn": "10",
			"verseNumberAs": "ܝ",
			"verseText": "ܘܐ݇ܡܸܪܵܐ ܠܐܲܒ̣ܪܵܗܵܡ: ܛܪܘܿܕ ܠܐܵܗܵܐ ܚܹܕܲܡܬܵܐ ܘܠܒܪܘܼܢܘܼܗ̇: ܣܵܒܵܒ̇ ܕܠܹܐ ܝܵܪܸܬ ܒܪܘܼܢܵܐ ܕܐܵܗܵܐ ܚܹܕܲܡܬܵܐ ܥܲܡ ܒܪܘܼܢܝܼ: ܥܲܡ ܐܝܼܣܚܵܩ."
		},
		{
			"verseNumberEn": "11",
			"verseNumberAs": "ܝܐ",
			"verseText": "ܘܚܸܪܒܵܐ ܡܘܼܒܝܸܢܹܐ ܪܵܒܵܐ ܐܵܗܵܐ ܚܲܒ̇ܪܵܐ ܒܥܲܝܢܹ̈ܐ ܕܐܲܒ̣ܪܵܗܵܡ: ܥܲܠ ܗܲܓ̰ܼܿܬ ܕܒܪܘܼܢܘܼܗܝ."
		},
		{
			"verseNumberEn": "12",
			"verseNumberAs": "ܝܒ",
			"verseText": "ܘܐ݇ܡܸܪܹܐ ܐܲܠܵܗܵܐ ܠܐܲܒ̣ܪܵܗܵܡ: ܠܵܐ ܡܲܒܝܸܢܵܐ ܚܸܪܒܵܐ ܒܥܲܝ̈ܢܘܼܟ ܒܘܼܬ ܝܵܠܵܐ: ܘܒܘܼܬ ܚܹܕܲܡܬܘܼܟ. ܟܠ ܕܐܵܡܪܵܐ ܠܘܼܟ ܣܲܪܵܐ: ܫܡܥܝܼ ܒܩܵܠܘܼܗ̇: ܣܵܒܵܒ̇ ܕܒܐܝܼܣܚܵܩ ܒܸܬ ܦܵܝܸܫ ܩܸܪܝܵܐ ܐܸܠܘܼܟ ܙܲܪܥܵܐ."
		},
		{
			"verseNumberEn": "13",
			"verseNumberAs": "ܝܓ",
			"verseText": "ܘܐܘܼܦ ܒܪܘܼܢܵܐ ܕܚܹܕܲܡܬܵܐ ܠܛܵܝܸܦܵܐ ܒܸܬ ܥܵܒ̣ܕܸ‍ܢ‍ܹܗ: ܣܵܒܵܒ̇ ܕܙܲܪܥܘܼܟ ܝܼܠܹܐ."
		},
		{
			"verseNumberEn": "14",
			"verseNumberAs": "ܝܕ",
			"verseText": "ܘܩܸܡܠܹܐ ܓ̰ܼܿܠܕܹܐ ܐܲܒ̣ܪܵܗܵܡ ܒܨܲܦܪܵܐ: ܘܫܩܸܠܹܐ ܠܲܚܡܵܐ ܘܓܘܼܕܵܐ ܕܡ̈ܝܼܵܐ: ܘܝܸܗܒܸܠܹܐ ܩܵܐ ܗܵܓ̣ܵܪ: ܡܘܼܬܸܒ̣ܠܹܐ ܥܲܠ ܪܘܼܥܫܘܼܗ̇: ܘܠܝܵܠܵܐ: ܘܫܘܼܕܪܵܠܹܐ. ܘܐ݇ܙܸܠܵܐ: ܘܚܠܸܛܠܵܐ ܓܵܘ ܒܲܪܝܼܵܐ ܕܒܹܪܫܒܲܥ."
		},
		{
			"verseNumberEn": "15",
			"verseNumberAs": "ܝܗ",
			"verseText": "ܘܬܸܡܠܘܿܢ ܡ̈ܝܼܵܐ ܡ̣ܢ ܓܘܼܕܵܐ: ܘܪܘܼܦܹܠܵܐ ܠܝܵܠܵܐ ܬܚܘܿܬ ܚܕܵܐ ܡ̣ܢ ܟ̰ܵܠܘܿܘܹ̈ܐ."
		},
		{
			"verseNumberEn": "16",
			"verseNumberAs": "ܝܘ",
			"verseText": "ܘܐ݇ܙܸܠܵܐ: ܘܝ݇ܬܸܒ̣ܠܵܐ ܗ̇ܝ ܡ̣ܢ ܠܒܲܪܩܘܼܠ: ܪܸܚܩܵܐ ܐܲܝܟ ܪܲܦܵܝܬܵܐ ܒܩܸܫܬܵܐ: ܣܵܒܵܒ̇ ܕܐ݇ܡܸܪܵܐ: ܠܵܐ ܚܵܙܝܵܢ ܒܡܵܘܬܵܐ ܕܝܵܠܵܐ. ܘܝ݇ܬܸܒ̣ܠܵܐ ܡ̣ܢ ܠܒܲܪܩܘܼܠܝ: ܘܡܘܼܪܸܡܠܵܐ ܩܵܠܘܼܗ̇ ܘܒܟܹܠܵܐ."
		},
		{
			"verseNumberEn": "17",
			"verseNumberAs": "ܝܙ",
			"verseText": "ܘܫܡܸܥܠܹܐ ܐܲܠܵܗܵܐ ܩܵܠܹܗ ܕܝܵܠܵܐ: ܘܩܪܹܠܹܐ ܡܲܠܲܐܟܹܗ ܕܐܲܠܵܗܵܐ ܠܗܵ‍ܓ̣ܵܪ ܡ̣ܢ ܫܡܲܝܵܐ: ܘܐ݇ܡܸܪܹܐ ܐܸܠܵܗ̇: ܡܵܐ ܠܵܟ̣ܝ: ܗܵ‍ܓ̣ܵܪ: ܠܵܐ ܙܵܕܥܝܲܬܝ: ܣܵܒܵܒ̇ ܕܫܡܸܥܠܹܐ ܐܲܠܵܗܵܐ ܠܩܵܠܵܐ ܕܝܵܠܵܐ ܒܗ̇ܝ ܕܘܼܟܵܐ ܕܝܼܠܹܐ."
		},
		{
			"verseNumberEn": "18",
			"verseNumberAs": "ܝܚ",
			"verseText": "ܩܘܼܡ݇ܝ: ܫܩܘܿܠܝ ܠܝܵܠܵܐ: ܘܕܒ̣ܘܿܩܝ ܐܝܼܕܵܟ̣ܝ ܒܝ̣ܹܗ: ܣܵܒܵܒ̇ ܕܠܛܵܝܸܦܵܐ ܓܘܼܪܵܐ ܒܸܬ ܥܵܒ̣ܕܸ‍ܢܹܗ."
		},
		{
			"verseNumberEn": "19",
			"verseNumberAs": "ܝܛ",
			"verseText": "ܘܦܬܸܚܠܹܐ ܐܲܠܵܗܵܐ ܠܥܲܝܢ̈ܘܼܗ̇: ܘܚܙܹܠܵܐ ܒܹܪܵܐ ܕܡ̈ܝܼܵܐ: ܘܐ݇ܙܸܠܵܐ ܘܡܠܹܠܵܐ ܠܓܘܼܕܵܐ ܡ̈ܝܼܵܐ: ܘܡܘܼܫܬܹܠܵܐ ܠܝܵܠܵܐ."
		},
		{
			"verseNumberEn": "20",
			"verseNumberAs": "ܟ",
			"verseText": "ܘܗ݇ܘܹܠܹܐ ܐܲܠܵܗܵܐ ܥܲܡ ܝܵܠܵܐ: ܘܓܘܼܪܘܸܣܠܹܐ ܘܝ݇ܬܸܒ̣ܠܹܐ ܓܵܘ ܒܲܪܝܼܵܐ: ܘܗ݇ܘܹܠܹܐ ܓܲܪܘܘܼܣܹܐ ܪܲܦܵܢܵܐ ܒܩܸܫܬܵܐ."
		},
		{
			"verseNumberEn": "21",
			"verseNumberAs": "ܟܐ",
			"verseText": "ܘܝ݇ܬܸܒ̣ܠܹܐ ܓܵܘ ܒܲܪܝܼܵܐ ܕܦܵܪܵ‍ܢ: ܘܫܩܸܠܵܐ ܩܵܬܹܗ ܝܸܡܘܼܗܝ ܒܲܟ̣ܬܵܐ ܡ̣ܢ ܐܲܪܥܵܐ ܕܡܸܨܪܹܝܢ."
		},
		{
			"verseNumberEn": "22",
			"verseNumberAs": "ܟܒ",
			"verseText": "ܘܗ݇ܘܹܠܵܐ ܒܗ̇ܘ ܙܲܒ̣ܢܵܐ: ܘܐ݇ܡܸܪܹܐ ܐܲܒ̣ܝܼܡܲܠܟ ܘܦܝܼܟܸܠ ܪܲܒܚܲܝܠܹܗ ܠܐܲܒ̣ܪܵܗܵܡ: ܒܹܐܡܵܪܵܐ: ܐܲܠܵܗܵܐ ܥܲܡܘܼܟ ܝܼܠܹܐ ܒܟ̇ܠ ܕܒܸܥܒ̣ܵܕܵܐ ܝ݇ܘܸܬ."
		},
		{
			"verseNumberEn": "23",
			"verseNumberAs": "ܟܓ",
			"verseText": "ܘܐܵܕܝܵܐ ܝ݇ܡܝܼ ܐܸܠܝܼ ܒܐܲܠܵܗܵܐ ܠܲܐܟ̣ܵܐ: ܐܸ‍ܢ ܕܵܓܠܸܬ ܒܝܼܝܼ: ܘܒܙܲܪܥܝܼ: ܘܒܣܸܢܣܝܼܠܝܼ. ܐܲܝܟ ܫܵܦܵܩܲܬ ܕܥܒܸܕܠܝܼ ܥܲܡܘܼܟ ܥܵܒ̣ܕܸܬ ܥܲܡܝܼ: ܘܥܲܡ ܐܲܪܥܵܐ ܕܡܘܼܫܚܸܛܠܘܼܟ ܓܵܘܘܼܗ̇."
		},
		{
			"verseNumberEn": "24",
			"verseNumberAs": "ܟܕ",
			"verseText": "ܘܐ݇ܡܸܪܹܐ ܐܲܒ̣ܪܵܗܵܡ: ܐܵܢܵܐ ܒܸܬ ܝܵܡܸܢ."
		},
		{
			"verseNumberEn": "25",
			"verseNumberAs": "ܟܗ",
			"verseText": "ܘܡܘܼܢܟܸܣܠܹܐ ܐܲܒ̣ܪܵܗܵܡ ܠܐܲܒ̣ܝܼܡܲܠܟ: ܥܲܠ ܗܲܓ̰ܼܿܬ ܕܒܹܪܵܐ ܕܡ̈ܝܼܵܐ: ܕܫܩܸܠܘܿܢ ܒܚܲܝܠܵܐ ܕܹܓܵܘܵܬܹܐ ܕܐܲܒ̣ܝܼܡܲܠܟ."
		},
		{
			"verseNumberEn": "26",
			"verseNumberAs": "ܟܘ",
			"verseText": "ܘܐ݇ܡܸܪܹܐ ܐܲܒ̣ܝܼܡܲܠܟ: ܠܹܐ ܝܲܕܥܸܢ ܡܵܢܝܼ ܥܒܸܕܠܹܐ ܐܵܗܵܐ ܫܘܼܠܵܐ: ܘܐܘܼܦ ܐܲܢ݇ܬ ܠܵܐ ܡܘܼܕܸܥܠܘܼܟ ܐܸܠܝܼ: ܘܐܘܼܦ ܐܵܢܵܐ ܠܵܐ ܫܡܸܥܠܝܼ ܫܒ̣ܘܿܩ ܡ̣ܢ ܐܸܕܝܘܼ ܝܘܿܡܵܐ."
		},
		{
			"verseNumberEn": "27",
			"verseNumberAs": "ܟܙ",
			"verseText": "ܘܫܩܸܠܹܐ ܐܲܒ̣ܪܵܗܵܡ ܥܸܪ̈ܒܹܐ ܘܬܵܘܪܹ̈ܐ: ܘܝܸܗܒܸܠܹܐ ܠܐܲܒ̣ܝܼܡܲܠܟ: ܘܩܛܸܥܠܘܿܢ ܬܸܪܘܵܝ ܩܵܘܠܵܐ."
		},
		{
			"verseNumberEn": "28",
			"verseNumberAs": "ܟܚ",
			"verseText": "ܘܡܘܼܟܠܹܠܹܐ ܐܲܒ̣ܪܵܗܵܡ ܠܫܲܒܲܥ ܦܹܐܪ̈ܝܼܵܬܹܐ ܕܥܸܪ̈ܒܹܐ ܒܢܲܦ̮ܫܵܝ."
		},
		{
			"verseNumberEn": "29",
			"verseNumberAs": "ܟܛ",
			"verseText": "ܘܐ݇ܡܸܪܹܐ ܐܲܒ̣ܝܼܡܲܠܟ ܠܐܲܒ̣ܪܵܗܵܡ: ܡܘܼܕܝܼ ܝ݇ܢܵܐ ܐܲܢܹܐ ܫܲܒܲܥ ܦܹܐܪ̈ܝܼܵܬܹܐ: ܕܡܘܼܟܠܝܼܵܝ ܝ݇ܘܸܬ ܒܢܲܦ̮ܫܵܝ:"
		},
		{
			"verseNumberEn": "30",
			"verseNumberAs": "ܠ",
			"verseText": "ܘܐ݇ܡܸܪܹܐ: ܩܵܐ ܕܫܲܒܲܥ ܦܹܐܪ̈ܝܼܵܬܹܐ ܫܵܩܠܸܬ ܡ̣ܢ ܐܝܼܕܝܼ: ܕܗܵܘܝܵܐ ܐܸܠܝܼ ܠܣܵܗܕܘܼܬܵܐ: ܕܐܵܢܵܐ ܚܦܝܼܪܘܼܗܝ ܝ݇ܘܸ‍ܢ ܐܵܗܵܐ ܒܹܪܵܐ."
		},
		{
			"verseNumberEn": "31",
			"verseNumberAs": "ܠܐ",
			"verseText": "ܒܘܼܬ ܕܐܵܗܵܐ: ܩܪܹܠܹܐ ܠܗ̇ܝ ܕܘܼܟܵܐ: ܒܹܪܫܒܲܥ: ܣܵܒܵܒ̇ ܕܬܵܡܵܐ ܝ݇ܡܹܠܘܿܢ ܬܸܪܘܵܝ."
		},
		{
			"verseNumberEn": "32",
			"verseNumberAs": "ܠܒ",
			"verseText": "ܘܩܛܸܥܠܘܿܢ ܩܵܘܠܵܐ ܒܒܹܪܫܒܲܥ: ܘܩܸܡܠܹܐ ܐܒ̣ܝܼܡܲܠܟ ܘܦܝܼܟܸܠ ܪܲܒܚܲܝܠܹܗ: ܘܕܸܪܘܿܢ ܠܐܲܪܥܵܐ ܕܦܠܸܫܬܵܝܹ̈ܐ."
		},
		{
			"verseNumberEn": "33",
			"verseNumberAs": "ܠܓ",
			"verseText": "ܘܢܨܸܒ̣ܠܹܐ ܠܘܼܙܵܐ ܒܒܹܪܫܒܲܥ: ܘܩܪܹܠܹܐ ܬܵܡܵܐ ܒܫܸܡܵܐ ܕܡܵܪܝܵܐ ܐܲܠܵܗܵܐ ܕܥܵܠܲܡ."
		},
		{
			"verseNumberEn": "34",
			"verseNumberAs": "ܠܕ",
			"verseText": "ܘܡܘܼܫܚܸܛܠܹܐ ܐܲܒ̣ܪܵܗܵܡ ܒܐܲܪܥܵܐ ܕܦܠܸܫܬܵܝܹ̈ܐ ܝܘܿܡܵܢܹ̈ܐ ܪܵܒܵܐ."
		}
	]
}
